kaiju_app/__init__.py
kaiju_app/app.py
kaiju_app/bases.py
kaiju_app/configurator.py
kaiju_app/loader.py
kaiju_app/py.typed
kaiju_app/utils.py
kaiju_app-0.1.5.dist-info/LICENSE
kaiju_app-0.1.5.dist-info/METADATA
kaiju_app-0.1.5.dist-info/WHEEL
kaiju_app-0.1.5.dist-info/top_level.txt
kaiju_app-0.1.5.dist-info/RECORD
