Metadata-Version: 2.1
Name: kaiju-app
Version: 0.1.5
Summary: Python modular application and services
Home-page: https://github.com/violet-black/kaiju-app
Author: violetblackdev@gmail.com
License: MIT
Keywords: application,microservice,asyncio,infrastructure
Classifier: Development Status :: 3 - Alpha
Classifier: License :: OSI Approved :: MIT License
Classifier: Operating System :: MacOS
Classifier: Operating System :: Microsoft
Classifier: Operating System :: POSIX
Classifier: Programming Language :: Python
Classifier: Programming Language :: Python :: 3
Classifier: Programming Language :: Python :: 3 :: Only
Classifier: Programming Language :: Python :: 3.11
Classifier: Programming Language :: Python :: 3.12
Classifier: Programming Language :: Python :: 3.13
Classifier: Programming Language :: Python :: Implementation :: CPython
Requires-Python: >=3.11
License-File: LICENSE
Requires-Dist: template-dict
Requires-Dist: uvlog
Requires-Dist: kaiju-scheduler
Provides-Extra: dev
Requires-Dist: pip-tools ; extra == 'dev'
Requires-Dist: tox ; extra == 'dev'
Requires-Dist: mypy ; extra == 'dev'
Requires-Dist: isort ; extra == 'dev'
Requires-Dist: black ; extra == 'dev'
Requires-Dist: pre-commit ; extra == 'dev'
Provides-Extra: docs
Requires-Dist: sphinx ; extra == 'docs'
Requires-Dist: python-docs-theme ; extra == 'docs'
Requires-Dist: m2r2 ; extra == 'docs'
Provides-Extra: test
Requires-Dist: pytest ; extra == 'test'
Requires-Dist: coverage ; extra == 'test'
Requires-Dist: pytest-asyncio ; extra == 'test'
